serializer/__init__.py
serializer/data_packer/__init__.py
serializer/data_packer/consts.py
serializer/data_packer/packer.py
serializer/serializers/__init__.py
serializer/serializers/json_serializer.py
serializer/serializers/serializer_factory.py
serializer/serializers/serializer_meta.py
serializer/serializers/serializer_shell.py
serializer/serializers/xml_serializer.py
serializer_bahamolau-1.0.dist-info/METADATA
serializer_bahamolau-1.0.dist-info/WHEEL
serializer_bahamolau-1.0.dist-info/top_level.txt
serializer_bahamolau-1.0.dist-info/RECORD
