Metadata-Version: 2.1
Name: serializer-bahamolau
Version: 1.0
Summary: JSON/XML serializer
Home-page: UNKNOWN
Author: Mikhail Bahamolau
License: UNKNOWN
Platform: UNKNOWN
